setup.py
django_third_party.egg-info/PKG-INFO
django_third_party.egg-info/SOURCES.txt
django_third_party.egg-info/dependency_links.txt
django_third_party.egg-info/requires.txt
django_third_party.egg-info/top_level.txt
djthirdparty/__init__.py
djthirdparty/admin.py
djthirdparty/context_processors.py
djthirdparty/models.py
djthirdparty/views.py
djthirdparty/migrations/0001_initial.py
djthirdparty/migrations/__init__.py