Metadata-Version: 1.1
Name: django-third-party
Version: 0.1.0
Summary: Add third party scripts and css to specific paths via db.
Home-page: https://github.com/buddylindsey/django-third-party
Author: Buddy Lindsey
Author-email: buddy@buddylindsey.com
License: UNKNOWN
Platform: UNKNOWN
Classifier: Development Status :: 3 - Alpha
Classifier: Environment :: Web Environment
Classifier: Framework :: Django
Classifier: Framework :: Django :: 1.8
Classifier: Intended Audience :: Developers
Classifier: License :: OSI Approved :: MIT License
Classifier: Natural Language :: English
Classifier: Operating System :: OS Independent
Classifier: Programming Language :: Python
Classifier: Programming Language :: Python :: 2.7
Classifier: Topic :: Internet :: WWW/HTTP :: Site Management
